{
  "2023-05-23": [],
  "2023-05-24": [
    {
      "id": "1",
      "name": "Artificial football field 1",
      "address": "177 Nguyen Xi, Binh Thanh, tp HCM ",
      "height": 50,
      "startTime": "14:00",
      "hours": "02:00",
      "userName": "Tran Phu Son",
      "day": "2022-11-24"
    }
  ],
  "2023-05-25": [
    {
      "id": "2",
      "name": "Artificial football field 2",
      "address": "177 Nguyen Xi, Binh Thanh, tp HCM ",
      "height": 50,
      "startTime": "14:00",
      "hours": "02:00",
      "userName": "Tran Phu Son",
      "day": "2022-11-25"
    },
    {
      "id": "2",
      "name": "Artificial football field 3",
      "address": "177 Nguyen Xi, Binh Thanh, tp HCM ",
      "height": 50,
      "startTime": "14:00",
      "hours": "02:00",
      "userName": "Tran Phu Son",
      "day": "2022-11-25"
    },
    {
      "id": "3",
      "name": "Artificial football field 4",
      "address": "177 Nguyen Xi, Binh Thanh, tp HCM ",
      "height": 50,
      "startTime": "14:00",
      "hours": "02:00",
      "userName": "Tran Phu Son",
      "day": "2022-11-25"
    }
  ],
  "2023-05-26": [
    {
      "id": "4",
      "name": "Artificial football field 5",
      "address": "177 Nguyen Xi, Binh Thanh, tp HCM ",
      "height": 50,
      "startTime": "14:00",
      "hours": "02:00",
      "userName": "Tran Phu Son",
      "day": "2022-11-26"
    },
    {
      "id": "5",
      "name": "Artificial football field 7",
      "address": "177 Nguyen Xi, Binh Thanh, tp HCM ",
      "height": 50,
      "startTime": "14:00",
      "hours": "02:00",
      "userName": "Tran Phu Son",
      "day": "2022-11-26"
    }
  ],
  "2023-05-27": [
    {
      "id": "6",
      "name": "Artificial football field 8",
      "address": "177 Nguyen Xi, Binh Thanh, tp HCM ",
      "height": 50,
      "startTime": "14:00",
      "hours": "02:00",
      "userName": "Tran Phu Son",
      "day": "2022-11-27"
    },
    {
      "id": "7",
      "name": "Artificial football field 9",
      "address": "177 Nguyen Xi, Binh Thanh, tp HCM ",
      "height": 50,
      "startTime": "14:00",
      "hours": "02:00",
      "userName": "Tran Phu Son",
      "day": "2022-11-27"
    }
  ],
  "2023-05-28": [
    {
      "id": "8",
      "name": "Artificial football field 10",
      "address": "177 Nguyen Xi, Binh Thanh, tp HCM ",
      "height": 50,
      "startTime": "14:00",
      "hours": "02:00",
      "userName": "Tran Phu Son",
      "day": "2022-11-28"
    }
  ]
}
